<?xml version="1.0" encoding="UTF-8"?>
<!DOCTYPE ChatMessages  SYSTEM "ChatMessagesDTD.dtd">

<ChatMessages>
  <Topic>Birthday Surprise</Topic>
  <Emotion>Happy</Emotion>
  <Message>Hey! Guess what? I just got the best birthday surprise!</Message>
  <Message>Really? What was it?</Message>
  <Message>My friends threw a surprise party for me!</Message>
  <Message>Wow, that’s amazing! Did you have fun?</Message>
  <Message>Oh, it was so much fun! We played games and had a huge cake!</Message>
  <Message>Sounds like a blast! What kind of cake?</Message>
  <Message>Chocolate, of course! My favorite!</Message>
  <Message>That’s awesome! I’m so happy for you!</Message>
  <Message>Thank you! I’m still smiling from ear to ear!</Message>
  <Message>Haha, you deserve it! Happy Birthday once again!</Message>
</ChatMessages>